tabdance/__init__.py
tabdance/base.py
tabdance/command.py
tabdance/config.py
tabdance/run.py
tabdance/tabdance.default.cfg
tabdance/update.py
tabdance/sql/check_exist_file.sql
tabdance/sql/compare_tds_version.sql
tabdance/sql/create_table.sql
tabdance/sql/drop_table.sql
tabdance/sql/insert_primary_key.sql
tabdance/sql/insert_tds_version.sql
tabdance/sql/select_table.sql
tabdance/sql/update_tds_version.sql
tabdance/sql/base/init_schema.sql
tabdance/sql/base/init_table.sql
tabdance/sql/td/copy_csv_to_table.sql
tabdance/sql/td/insert_target_from_temp.sql
tabdance/updownload/__init__.py
tabdance/updownload/base.py
tabdance/updownload/download.py
tabdance/updownload/ssh.py
tabdance/updownload/upload.py
tabdance-1.0.4.dist-info/LICENSE
tabdance-1.0.4.dist-info/METADATA
tabdance-1.0.4.dist-info/WHEEL
tabdance-1.0.4.dist-info/entry_points.txt
tabdance-1.0.4.dist-info/top_level.txt
tabdance-1.0.4.dist-info/RECORD
