Metadata-Version: 2.1
Name: tabdance
Version: 1.0.4
Summary: Table Data Syncer
Home-page: https://github.com/linewalks/tabdance
Author: Linewalks
Author-email: insu@linewalks.com
License: UNKNOWN
Platform: UNKNOWN
Requires-Python: >= 3.8
License-File: LICENSE
Requires-Dist: configparser
Requires-Dist: paramiko
Requires-Dist: pandas
Requires-Dist: psycopg2-binary
Requires-Dist: SQLAlchemy
